{
  "data": {
    "article": {},
    "attachments": {},
    "author_id": "1972656423021801472",
    "conversation_id": "2058355532021575699",
    "created_at": "2026-05-24T02:49:00.000Z",
    "edit_controls": {
      "editable_until": "2026-05-24T03:49:00.000Z",
      "edits_remaining": 5,
      "is_edit_eligible": false
    },
    "edit_history_tweet_ids": [
      "2058379710779031737"
    ],
    "entities": {
      "mentions": [
        {
          "end": 13,
          "id": "1753386090143354880",
          "start": 0,
          "username": "HanQWQ457437"
        }
      ]
    },
    "geo": {},
    "id": "2058379710779031737",
    "in_reply_to_user_id": "1753386090143354880",
    "lang": "zh",
    "note_tweet": {
      "entities": {}
    },
    "possibly_sensitive": false,
    "public_metrics": {
      "bookmark_count": 0,
      "impression_count": 0,
      "like_count": 0,
      "quote_count": 0,
      "reply_count": 0,
      "retweet_count": 0
    },
    "referenced_tweets": [
      {
        "id": "2058355532021575699",
        "type": "replied_to"
      }
    ],
    "reply_settings": "everyone",
    "text": "@HanQWQ457437 好帅！"
  },
  "includes": {
    "media": [
      {
        "height": 1122,
        "media_key": "3_2058355529840578560",
        "public_metrics": {},
        "type": "photo",
        "url": "https://pbs.twimg.com/media/HJC_cuGb0AA-PZJ.jpg",
        "width": 886
      }
    ],
    "tweets": [
      {
        "article": {},
        "attachments": {},
        "author_id": "1972656423021801472",
        "conversation_id": "2058355532021575699",
        "created_at": "2026-05-24T02:49:00.000Z",
        "edit_controls": {
          "editable_until": "2026-05-24T03:49:00.000Z",
          "edits_remaining": 5,
          "is_edit_eligible": false
        },
        "edit_history_tweet_ids": [
          "2058379710779031737"
        ],
        "entities": {
          "mentions": [
            {
              "end": 13,
              "id": "1753386090143354880",
              "start": 0,
              "username": "HanQWQ457437"
            }
          ]
        },
        "geo": {},
        "id": "2058379710779031737",
        "in_reply_to_user_id": "1753386090143354880",
        "lang": "zh",
        "note_tweet": {
          "entities": {}
        },
        "possibly_sensitive": false,
        "public_metrics": {
          "bookmark_count": 0,
          "impression_count": 0,
          "like_count": 0,
          "quote_count": 0,
          "reply_count": 0,
          "retweet_count": 0
        },
        "referenced_tweets": [
          {
            "id": "2058355532021575699",
            "type": "replied_to"
          }
        ],
        "reply_settings": "everyone",
        "text": "@HanQWQ457437 好帅！"
      },
      {
        "article": {},
        "attachments": {
          "media_keys": [
            "3_2058355529840578560"
          ]
        },
        "author_id": "1753386090143354880",
        "conversation_id": "2058355532021575699",
        "created_at": "2026-05-24T01:12:55.000Z",
        "edit_controls": {
          "editable_until": "2026-05-24T02:12:55.000Z",
          "edits_remaining": 5,
          "is_edit_eligible": true
        },
        "edit_history_tweet_ids": [
          "2058355532021575699"
        ],
        "entities": {
          "urls": [
            {
              "display_url": "pic.x.com/YJYQWGfjAt",
              "end": 87,
              "expanded_url": "https://x.com/HanQWQ457437/status/2058355532021575699/photo/1",
              "media_key": "3_2058355529840578560",
              "start": 64,
              "url": "https://t.co/YJYQWGfjAt"
            }
          ]
        },
        "geo": {},
        "id": "2058355532021575699",
        "lang": "zh",
        "note_tweet": {
          "entities": {}
        },
        "possibly_sensitive": false,
        "public_metrics": {
          "bookmark_count": 0,
          "impression_count": 81,
          "like_count": 9,
          "quote_count": 0,
          "reply_count": 2,
          "retweet_count": 0
        },
        "reply_settings": "everyone",
        "text": "我每天就这样什么都不做 就看着你 一直看着你 你在干什么呀 有没有和别人聊天 是不是在和别人玩呀 我会一直看着你的👁️👁️👁️ https://t.co/YJYQWGfjAt"
      }
    ],
    "users": [
      {
        "created_at": "2025-09-29T13:35:29.000Z",
        "description": "重度百合豚，河野裕狂热粉丝，lgbt友好，交友大欢迎！欢迎互关喵 08小女孩 很温良的入ww防走丢：@Ovojuhao",
        "entities": {
          "description": {
            "mentions": [
              {
                "end": 59,
                "start": 50,
                "username": "Ovojuhao"
              }
            ]
          },
          "url": {
            "urls": [
              {
                "display_url": "ngl.link/%E5%8F%A5%E5%8…",
                "end": 23,
                "expanded_url": "https://ngl.link/%E5%8F%A5%E5%8F%B7ovo",
                "start": 0,
                "url": "https://t.co/0WnDZR2odX"
              }
            ]
          }
        },
        "id": "1972656423021801472",
        "location": "架见崎站南检票口前",
        "name": "句号Ovo",
        "pinned_tweet_id": "2012765004865626462",
        "profile_image_url": "https://pbs.twimg.com/profile_images/1972656867710255104/ivD4OJ6f_normal.jpg",
        "protected": false,
        "public_metrics": {
          "followers_count": 227,
          "following_count": 354,
          "like_count": 485,
          "listed_count": 1,
          "media_count": 48,
          "tweet_count": 912
        },
        "url": "https://t.co/0WnDZR2odX",
        "username": "Ovoyachiyo",
        "verified": false
      },
      {
        "created_at": "2024-02-02T11:53:25.000Z",
        "description": "08年2月/大一/性别男  欢迎找我聊天，我很需要人类陪我🥺  🚪100cny🤤支持加密货币🤤 欢迎来加我的tg小群 https://t.co/LDm1zGibSQ",
        "entities": {
          "description": {
            "urls": [
              {
                "display_url": "t.me/aaaaaHanqwq",
                "end": 82,
                "expanded_url": "https://t.me/aaaaaHanqwq",
                "start": 59,
                "url": "https://t.co/LDm1zGibSQ"
              }
            ]
          }
        },
        "id": "1753386090143354880",
        "location": "City of London, London",
        "name": "Accelerator🇦🇺",
        "pinned_tweet_id": "2038355860112761162",
        "profile_image_url": "https://pbs.twimg.com/profile_images/2058354606653227008/A1Hj4hES_normal.jpg",
        "protected": false,
        "public_metrics": {
          "followers_count": 1032,
          "following_count": 1021,
          "like_count": 2580,
          "listed_count": 0,
          "media_count": 68,
          "tweet_count": 744
        },
        "username": "HanQWQ457437",
        "verified": true
      }
    ]
  }
}