{
  "data": {
    "article": {},
    "attachments": {},
    "author_id": "1972656423021801472",
    "conversation_id": "2049624486421332048",
    "created_at": "2026-04-30T10:16:24.000Z",
    "edit_controls": {
      "editable_until": "2026-04-30T11:16:24.000Z",
      "edits_remaining": 5,
      "is_edit_eligible": false
    },
    "edit_history_tweet_ids": [
      "2049794995012690201"
    ],
    "entities": {
      "mentions": [
        {
          "end": 13,
          "id": "1843360729199718404",
          "start": 0,
          "username": "longlongp97w"
        }
      ]
    },
    "geo": {},
    "id": "2049794995012690201",
    "in_reply_to_user_id": "1843360729199718404",
    "lang": "zh",
    "note_tweet": {
      "entities": {}
    },
    "possibly_sensitive": false,
    "public_metrics": {
      "bookmark_count": 0,
      "impression_count": 0,
      "like_count": 0,
      "quote_count": 0,
      "reply_count": 0,
      "retweet_count": 0
    },
    "referenced_tweets": [
      {
        "id": "2049624486421332048",
        "type": "replied_to"
      }
    ],
    "reply_settings": "everyone",
    "text": "@longlongp97w 抱抱龙，人不会突然改变只能证明她本来就是那样，你已经避免产生更多的痛苦了"
  },
  "includes": {
    "media": [
      {
        "height": 1152,
        "media_key": "3_2049624481383997440",
        "public_metrics": {},
        "type": "photo",
        "url": "https://pbs.twimg.com/media/HHG6mz_WYAA1Ckz.jpg",
        "width": 2048
      }
    ],
    "tweets": [
      {
        "article": {},
        "attachments": {},
        "author_id": "1972656423021801472",
        "conversation_id": "2049624486421332048",
        "created_at": "2026-04-30T10:16:24.000Z",
        "edit_controls": {
          "editable_until": "2026-04-30T11:16:24.000Z",
          "edits_remaining": 5,
          "is_edit_eligible": false
        },
        "edit_history_tweet_ids": [
          "2049794995012690201"
        ],
        "entities": {
          "mentions": [
            {
              "end": 13,
              "id": "1843360729199718404",
              "start": 0,
              "username": "longlongp97w"
            }
          ]
        },
        "geo": {},
        "id": "2049794995012690201",
        "in_reply_to_user_id": "1843360729199718404",
        "lang": "zh",
        "note_tweet": {
          "entities": {}
        },
        "possibly_sensitive": false,
        "public_metrics": {
          "bookmark_count": 0,
          "impression_count": 0,
          "like_count": 0,
          "quote_count": 0,
          "reply_count": 0,
          "retweet_count": 0
        },
        "referenced_tweets": [
          {
            "id": "2049624486421332048",
            "type": "replied_to"
          }
        ],
        "reply_settings": "everyone",
        "text": "@longlongp97w 抱抱龙，人不会突然改变只能证明她本来就是那样，你已经避免产生更多的痛苦了"
      },
      {
        "article": {},
        "attachments": {
          "media_keys": [
            "3_2049624481383997440"
          ]
        },
        "author_id": "1843360729199718404",
        "conversation_id": "2049624486421332048",
        "created_at": "2026-04-29T22:58:52.000Z",
        "edit_controls": {
          "editable_until": "2026-04-29T23:58:52.000Z",
          "edits_remaining": 5,
          "is_edit_eligible": true
        },
        "edit_history_tweet_ids": [
          "2049624486421332048"
        ],
        "entities": {
          "urls": [
            {
              "display_url": "pic.x.com/g2ftcA67xY",
              "end": 85,
              "expanded_url": "https://x.com/longlongp97w/status/2049624486421332048/photo/1",
              "media_key": "3_2049624481383997440",
              "start": 62,
              "url": "https://t.co/g2ftcA67xY"
            }
          ]
        },
        "geo": {},
        "id": "2049624486421332048",
        "lang": "zh",
        "note_tweet": {
          "entities": {}
        },
        "possibly_sensitive": true,
        "public_metrics": {
          "bookmark_count": 0,
          "impression_count": 109,
          "like_count": 6,
          "quote_count": 0,
          "reply_count": 2,
          "retweet_count": 0
        },
        "reply_settings": "everyone",
        "text": "一月份在韩国玩的时候，为什么，要给我留下那么好的回忆，为什么，人会变得这么快，为什么，我偏偏是个恋久的人，为什么，我还活着 https://t.co/g2ftcA67xY"
      }
    ],
    "users": [
      {
        "created_at": "2025-09-29T13:35:29.000Z",
        "description": "重度百合豚，河野裕狂热粉丝，lgbt友好，交友大欢迎！欢迎互关喵 08小女孩 很温良的入ww",
        "entities": {
          "url": {
            "urls": [
              {
                "display_url": "ngl.link/%E5%8F%A5%E5%8…",
                "end": 23,
                "expanded_url": "https://ngl.link/%E5%8F%A5%E5%8F%B7ovo",
                "start": 0,
                "url": "https://t.co/0WnDZR2odX"
              }
            ]
          }
        },
        "id": "1972656423021801472",
        "location": "架见崎站南检票口前",
        "name": "句号Ovo",
        "pinned_tweet_id": "2012765004865626462",
        "profile_image_url": "https://pbs.twimg.com/profile_images/1972656867710255104/ivD4OJ6f_normal.jpg",
        "protected": false,
        "public_metrics": {
          "followers_count": 181,
          "following_count": 285,
          "like_count": 366,
          "listed_count": 1,
          "media_count": 37,
          "tweet_count": 653
        },
        "url": "https://t.co/0WnDZR2odX",
        "username": "Ovoyachiyo",
        "verified": false
      },
      {
        "created_at": "2024-10-07T18:40:31.000Z",
        "description": "‼️‼️‼️如果我的帖子让您感到不适，请立即拉黑我不要恶评，谢谢‼️‼️‼️双，但是自救成功，目前稳定（这段时间被恶心了应该不稳定了）ps.龙的聊天能力堪比人机，龙喜欢被夸🥰,然后我不是同！想多找互关呀，提问箱：https://t.co/oCgXhmsRO0\n小号：@longrc7x  #碎碎念",
        "entities": {
          "description": {
            "hashtags": [
              {
                "end": 148,
                "start": 144,
                "tag": "碎碎念"
              }
            ],
            "mentions": [
              {
                "end": 142,
                "start": 133,
                "username": "longrc7x"
              }
            ],
            "urls": [
              {
                "display_url": "ngl.link/jjjjjjjj14864",
                "end": 129,
                "expanded_url": "https://ngl.link/jjjjjjjj14864",
                "start": 106,
                "url": "https://t.co/oCgXhmsRO0"
              }
            ]
          },
          "url": {
            "urls": [
              {
                "display_url": "ngl.link/jjjjjjjj14864",
                "end": 23,
                "expanded_url": "https://ngl.link/jjjjjjjj14864",
                "start": 0,
                "url": "https://t.co/oCgXhmsRO0"
              }
            ]
          }
        },
        "id": "1843360729199718404",
        "location": "阿美莉卡",
        "name": "龙long",
        "pinned_tweet_id": "2045270964162699734",
        "profile_image_url": "https://pbs.twimg.com/profile_images/2041004546806468608/r_cGy1V2_normal.jpg",
        "protected": false,
        "public_metrics": {
          "followers_count": 110,
          "following_count": 143,
          "like_count": 7941,
          "listed_count": 0,
          "media_count": 155,
          "tweet_count": 1514
        },
        "url": "https://t.co/oCgXhmsRO0",
        "username": "longlongp97w",
        "verified": false
      }
    ]
  }
}